gaiaAssociation/__init__.py
gaiaAssociation/gaiaAssociation.py
gaiaAssociation-1.2.30.dist-info/LICENSE
gaiaAssociation-1.2.30.dist-info/METADATA
gaiaAssociation-1.2.30.dist-info/WHEEL
gaiaAssociation-1.2.30.dist-info/entry_points.txt
gaiaAssociation-1.2.30.dist-info/top_level.txt
gaiaAssociation-1.2.30.dist-info/RECORD
